[
 {
  "sid":"SupervisorFSM_RX:95:556",
  "inspector":{
   "params":[
    "FixedHeight",
    "FixedWidth",
    "DropShadow",
    "Description",
    "Document"
   ],
   "values":[
    false,
    false,
    false,
    "",
    ""
   ],
   "tabs":[
    "General",
    "Documentation"
   ],
   "tabs_idx":[
    0,
    3
   ]
  },
  "viewer":{
   "jshandler":"webview/handlers/ElementHandler"
  },
  "obj_viewer":[
  ],
  "finder":[
  ]
 },
 {
  "sid":"SupervisorFSM_RX:95:558",
  "inspector":{
   "params":[
    "InlineOption",
    "LabelString",
    "SaturateOnIntegerOverflow",
    "EmlDefaultFimath",
    "Description",
    "Document"
   ],
   "values":[
    "Auto",
    "boardOk=isBoardConfigured",
    true,
    "Same as MATLAB Default",
    "",
    ""
   ],
   "tabs":[
    "General",
    "Documentation"
   ],
   "tabs_idx":[
    0,
    4
   ]
  },
  "viewer":{
   "jshandler":"webview/handlers/ElementHandler"
  },
  "obj_viewer":{
   "code":"function boardOk=isBoardConfigured\n%check here if all board services are ready \nboardOk=true;\nend",
   "code_sid":"SupervisorFSM_RX:95:558"
  },
  "finder":[
  ]
 },
 {
  "sid":"SupervisorFSM_RX:95:559",
  "inspector":{
   "params":[
    "HasOutputData",
    "OutputMonitoringMode",
    "InlineOption",
    "LabelString",
    "DataLogging",
    "TestPoint",
    "NameMode",
    "LoggingName",
    "LimitDataPoints",
    "MaxPoints",
    "DecimateData",
    "Decimation",
    "Description",
    "Document"
   ],
   "values":[
    false,
    "SelfActivity",
    "Auto",
    "NotConfigured\nentry: \nBoardSt = BoardState.NotConfigured;",
    false,
    false,
    "SignalName",
    "STATE_HANDLER.NotConfigured",
    false,
    5000,
    false,
    2,
    "",
    ""
   ],
   "tabs":[
    "General",
    "Logging",
    "Documentation"
   ],
   "tabs_idx":[
    0,
    4,
    12
   ]
  },
  "viewer":{
   "jshandler":"webview/handlers/ElementHandler"
  },
  "obj_viewer":[
  ],
  "finder":[
  ]
 },
 {
  "sid":"SupervisorFSM_RX:95:560",
  "inspector":{
   "params":[
    "HasOutputData",
    "OutputMonitoringMode",
    "InlineOption",
    "LabelString",
    "DataLogging",
    "TestPoint",
    "NameMode",
    "LoggingName",
    "LimitDataPoints",
    "MaxPoints",
    "DecimateData",
    "Decimation",
    "Description",
    "Document"
   ],
   "values":[
    false,
    "SelfActivity",
    "Auto",
    "Fault\nentry: \nBoardSt = BoardState.Fault;",
    false,
    false,
    "SignalName",
    "STATE_HANDLER.Fault",
    false,
    5000,
    false,
    2,
    "",
    ""
   ],
   "tabs":[
    "General",
    "Logging",
    "Documentation"
   ],
   "tabs_idx":[
    0,
    4,
    12
   ]
  },
  "viewer":{
   "jshandler":"webview/handlers/ElementHandler"
  },
  "obj_viewer":[
  ],
  "finder":[
  ]
 },
 {
  "sid":"SupervisorFSM_RX:95:561",
  "inspector":{
   "params":[
    "HasOutputData",
    "OutputMonitoringMode",
    "InlineOption",
    "LabelString",
    "DataLogging",
    "TestPoint",
    "NameMode",
    "LoggingName",
    "LimitDataPoints",
    "MaxPoints",
    "DecimateData",
    "Decimation",
    "Description",
    "Document"
   ],
   "values":[
    false,
    "SelfActivity",
    "Auto",
    "Configured\nentry: \nBoardSt = BoardState.Configured;\n",
    false,
    false,
    "SignalName",
    "STATE_HANDLER.Configured",
    false,
    5000,
    false,
    2,
    "",
    ""
   ],
   "tabs":[
    "General",
    "Logging",
    "Documentation"
   ],
   "tabs_idx":[
    0,
    4,
    12
   ]
  },
  "viewer":{
   "jshandler":"webview/handlers/ElementHandler"
  },
  "obj_viewer":[
  ],
  "finder":[
  ]
 },
 {
  "sid":"SupervisorFSM_RX:95:549",
  "inspector":{
   "params":[
    "ExecutionOrder",
    "IsVariant",
    "LabelString",
    "Description",
    "Document"
   ],
   "values":[
    1,
    false,
    "",
    "",
    ""
   ],
   "tabs":[
    "Parameter Attributes"
   ],
   "tabs_idx":0
  },
  "viewer":{
   "jshandler":"webview/handlers/ElementHandler"
  },
  "obj_viewer":[
  ],
  "finder":[
  ]
 },
 {
  "sid":"SupervisorFSM_RX:95:550",
  "inspector":{
   "params":[
    "ExecutionOrder",
    "IsVariant",
    "LabelString",
    "Description",
    "Document"
   ],
   "values":[
    1,
    false,
    "BoardFaultEvent",
    "",
    ""
   ],
   "tabs":[
    "Parameter Attributes"
   ],
   "tabs_idx":0
  },
  "viewer":{
   "jshandler":"webview/handlers/ElementHandler"
  },
  "obj_viewer":[
  ],
  "finder":[
  ]
 },
 {
  "sid":"SupervisorFSM_RX:95:551",
  "inspector":{
   "params":[
    "ExecutionOrder",
    "IsVariant",
    "LabelString",
    "Description",
    "Document"
   ],
   "values":[
    1,
    false,
    "[!isBoardConfigured()]",
    "",
    ""
   ],
   "tabs":[
    "Parameter Attributes"
   ],
   "tabs_idx":0
  },
  "viewer":{
   "jshandler":"webview/handlers/ElementHandler"
  },
  "obj_viewer":[
  ],
  "finder":[
  ]
 },
 {
  "sid":"SupervisorFSM_RX:95:552",
  "inspector":{
   "params":[
    "ExecutionOrder",
    "IsVariant",
    "LabelString",
    "Description",
    "Document"
   ],
   "values":[
    2,
    false,
    "[isBoardConfigured()]",
    "",
    ""
   ],
   "tabs":[
    "Parameter Attributes"
   ],
   "tabs_idx":0
  },
  "viewer":{
   "jshandler":"webview/handlers/ElementHandler"
  },
  "obj_viewer":[
  ],
  "finder":[
  ]
 },
 {
  "sid":"SupervisorFSM_RX:95:553",
  "inspector":{
   "params":[
    "ExecutionOrder",
    "IsVariant",
    "LabelString",
    "Description",
    "Document"
   ],
   "values":[
    2,
    false,
    "",
    "",
    ""
   ],
   "tabs":[
    "Parameter Attributes"
   ],
   "tabs_idx":0
  },
  "viewer":{
   "jshandler":"webview/handlers/ElementHandler"
  },
  "obj_viewer":[
  ],
  "finder":[
  ]
 },
 {
  "sid":"SupervisorFSM_RX:95:554",
  "inspector":{
   "params":[
    "ExecutionOrder",
    "IsVariant",
    "LabelString",
    "Description",
    "Document"
   ],
   "values":[
    1,
    false,
    "OutOfBoardFaultEvent",
    "",
    ""
   ],
   "tabs":[
    "Parameter Attributes"
   ],
   "tabs_idx":0
  },
  "viewer":{
   "jshandler":"webview/handlers/ElementHandler"
  },
  "obj_viewer":[
  ],
  "finder":[
  ]
 },
 {
  "sid":"SupervisorFSM_RX:95:555",
  "inspector":{
   "params":[
    "ExecutionOrder",
    "IsVariant",
    "LabelString",
    "Description",
    "Document"
   ],
   "values":[
    1,
    false,
    "BoardFaultEvent",
    "",
    ""
   ],
   "tabs":[
    "Parameter Attributes"
   ],
   "tabs_idx":0
  },
  "viewer":{
   "jshandler":"webview/handlers/ElementHandler"
  },
  "obj_viewer":[
  ],
  "finder":[
  ]
 }
]